HJRewardsBot/RewardsBot.py
HJRewardsBot/__init__.py
HJRewardsBot-0.2.8.dist-info/METADATA
HJRewardsBot-0.2.8.dist-info/WHEEL
HJRewardsBot-0.2.8.dist-info/top_level.txt
HJRewardsBot-0.2.8.dist-info/RECORD
