Metadata-Version: 2.1
Name: HJRewardsBot
Version: 0.2.8
Summary: Bing Rewards Bot by Hassan
Home-page: UNKNOWN
Author: Hassan jlilati
Author-email: <hassanjlilati10000@gmail.com>
License: UNKNOWN
Keywords: python,rewards
Platform: UNKNOWN
Classifier: Development Status :: 1 - Planning
Classifier: Intended Audience :: Developers
Classifier: Programming Language :: Python :: 3
Classifier: Operating System :: Microsoft :: Windows
Requires-Dist: webdriver-manager
Requires-Dist: selenium
Requires-Dist: requests
